pyten.py
pyten-0.1.0.dist-info/WHEEL
pyten-0.1.0.dist-info/METADATA
pyten-0.1.0.dist-info/RECORD
