Metadata-Version: 2.1
Name: pyten
Version: 0.1.0
Summary: Python 3.10 killer features
License: MIT
Author: Avi Lumelsky
Requires-Python: >=3.10,<4.0
Classifier: License :: OSI Approved :: MIT License
Classifier: Programming Language :: Python :: 3
Classifier: Programming Language :: Python :: 3.10
Requires-Dist: numpy (==1.19.4)
Requires-Dist: pyarrow (<2)
